pvmismatch/__init__.py
pvmismatch/version.py
pvmismatch/contrib/__init__.py
pvmismatch/contrib/module_mismatch_simulator.py
pvmismatch/contrib/tiled_reference_module.py
pvmismatch/contrib/gen_coeffs/__init__.py
pvmismatch/contrib/gen_coeffs/diode.py
pvmismatch/contrib/gen_coeffs/example.py
pvmismatch/contrib/gen_coeffs/two_diode.py
pvmismatch/docs/Makefile
pvmismatch/docs/conf.py
pvmismatch/docs/index.rst
pvmismatch/docs/make.bat
pvmismatch/pvmismatch_json/messagetext.English.json
pvmismatch/pvmismatch_json/validationConstants.json
pvmismatch/pvmismatch_lib/__init__.py
pvmismatch/pvmismatch_lib/bypassdevice.py
pvmismatch/pvmismatch_lib/pvcell.py
pvmismatch/pvmismatch_lib/pvconstants.py
pvmismatch/pvmismatch_lib/pvexceptions.py
pvmismatch/pvmismatch_lib/pvmodule.py
pvmismatch/pvmismatch_lib/pvstring.py
pvmismatch/pvmismatch_lib/pvsystem.py
pvmismatch/pvmismatch_lib/tamir.py
pvmismatch/pvmismatch_tk/__init__.py
pvmismatch/pvmismatch_tk/advCnf_tk.py
pvmismatch/pvmismatch_tk/pvapplication_tk.py
pvmismatch/pvmismatch_tk/pvexceptions.py
pvmismatch/pvmismatch_tk/pvmodule_tk.py
pvmismatch/pvmismatch_tk/pvstring_tk.py
pvmismatch/pvmismatch_tk/pvsystem_tk.py
pvmismatch/res/logo.png
pvmismatch/res/logo_bg.png
pvmismatch/res/logo_invert.png
pvmismatch-4.1.data/scripts/pv_tk.py
pvmismatch-4.1.dist-info/METADATA
pvmismatch-4.1.dist-info/RECORD
pvmismatch-4.1.dist-info/WHEEL
pvmismatch-4.1.dist-info/top_level.txt
