Metadata-Version: 2.1
Name: pvmismatch
Version: 4.1
Summary: PV Mismatch Calculator
Home-page: https://github.com/SunPower/PVMismatch
Author: mmikofski
Author-email: mark.mikofski@sunpowercorp.com
License: BSD 3-clause
Platform: UNKNOWN
Classifier: Development Status :: 4 - Beta
Classifier: License :: OSI Approved :: BSD License
Classifier: Operating System :: OS Independent
Classifier: Intended Audience :: Science/Research
Classifier: Programming Language :: Python
Classifier: Programming Language :: Python :: 2
Classifier: Programming Language :: Python :: 2.7
Classifier: Programming Language :: Python :: 3
Classifier: Programming Language :: Python :: 3.3
Classifier: Programming Language :: Python :: 3.4
Classifier: Programming Language :: Python :: 3.5
Classifier: Programming Language :: Python :: 3.6
Classifier: Topic :: Scientific/Engineering
Requires-Dist: numpy (>=1.13.3)
Requires-Dist: matplotlib (>=2.1.0)
Requires-Dist: scipy (>=1.0.0)
Requires-Dist: future (>=0.16.0)
Requires-Dist: six (>=1.11.0)
